coolmath/__init__.py
coolmath/operations.py
hashwinnath1810-0.1.0.dist-info/licenses/LICENSE
hashwinnath1810-0.1.0.dist-info/METADATA
hashwinnath1810-0.1.0.dist-info/WHEEL
hashwinnath1810-0.1.0.dist-info/top_level.txt
hashwinnath1810-0.1.0.dist-info/RECORD
