Metadata-Version: 2.4
Name: hashwinnath1810
Version: 0.1.0
Summary: A simple math library for basic operations
Author-email: Hashwinnath <your_email@example.com>
License: MIT
Project-URL: Homepage, https://github.com/yourusername/coolmath
Project-URL: Issues, https://github.com/yourusername/coolmath/issues
Keywords: math,utility,example
Classifier: Programming Language :: Python :: 3
Classifier: License :: OSI Approved :: MIT License
Classifier: Operating System :: OS Independent
Requires-Python: >=3.8
License-File: LICENSE
Dynamic: license-file
